sbstc/__init__.py
sbstc/exceptions.py
sbstc/sbstc.py
sbsTC-0.0.3.dist-info/LICENSE
sbsTC-0.0.3.dist-info/METADATA
sbsTC-0.0.3.dist-info/WHEEL
sbsTC-0.0.3.dist-info/top_level.txt
sbsTC-0.0.3.dist-info/RECORD
